GetNew/__init__.py
GetNew-0.0.1.dist-info/LICENSE.txt
GetNew-0.0.1.dist-info/METADATA
GetNew-0.0.1.dist-info/WHEEL
GetNew-0.0.1.dist-info/entry_points.txt
GetNew-0.0.1.dist-info/top_level.txt
GetNew-0.0.1.dist-info/RECORD
