Metadata-Version: 2.1
Name: GetNew
Version: 0.0.1
Summary: Get Version.
Home-page: https://github.com/LoveNishimiyaShouko/GetNew
Author: LoveNishimiyaShouko
Author-email: LoveNishimiyaShouko@LoveNishimiyaShouko.LoveNishimiyaShouko
License: AGPLv3
Project-URL: Documentation, https://github.com/LoveNishimiyaShouko/GetNew/tree/main/docs
Project-URL: Source, https://github.com/LoveNishimiyaShouko/GetNew/tree/main/code
Keywords: new version,latest version,version,get new version,get latest version,get version
Platform: UNKNOWN
Classifier: Development Status :: 5 - Production/Stable
Classifier: License :: OSI Approved :: GNU Affero General Public License v3 or later (AGPLv3+)
Classifier: Operating System :: OS Independent
Classifier: Programming Language :: Python
Requires-Python: >=3
Requires-Dist: requests
